Workbook

Sheet OVERHEAD
A1: HOJA DE ESTIMACIÓN DEL OVERHEAD DE LA EMPRESA
B3: PORCENTAJE DE COSTES INDIRECTOS (OVERHEAD) | F3: =+F23/C23 -> 0.38795477
B5: GASTOS DIRECTOS | E5: GASTOS INDIRECTOS
B6: CONCEPTO | C6: IMPORTE ANUAL | E6: CONCEPTO | F6: IMPORTE ANUAL
B7: Jefe de proyecto | C7: 80000 | E7: Comercial | F7: 80000
B8: Analista | C8: 120000 | E8: Gerente | F8: 45000
B9: Técnico de sistemas | C9: 32000 | E9: Administrativo | F9: 51000
B10: Técnico de datos | C10: 32000 | E10: Personal de mantenimiento | F10: 18000
B11: Programador | C11: 337500 | E11: Alquiler locales | F11: 36000
B12: Diseñador gráfico | C12: 20000 | E12: Seguros responsabilidad | F12: 1500
B13: Supervisor | C13: 35000 | E13: Seguridad | F13: 6000
B14: Seguridad social | C14: =0.3*(SUM(C7:C13)) -> 196950 | E14: Limpieza | F14: 3600
E15: Luz | F15: 12000
E16: Agua | F16: 2000
E17: Papelería | F17: 4800
E18: Publicidad | F18: 5000
E19: Impuestos | F19: 8000
E20: Seguridad social | F20: =0.3*(SUM(F7:F10)) -> 58200
B23: TOTAL | C23: =SUM(C7:C22) -> 853450 | E23: TOTAL | F23: =SUM(F7:F22) -> 331100

Sheet ESTIMACION
A1: HOJA DE ESTIMACIÓN ECONÓMICA DE PROYECTO
A3: DATOS DEL PROYECTO
A5: TITULO: | C5: DESARROLLO DE UN PORTAL WEB | J5: REFERENCIA: | L5: DES-01-2022
A6: CLIENTE: | C6: MEDIOLADO | J6: RESPONSABLE: | L6: PABLO Y CAMILO
A8: FECHA INICIO: | C8: 44562 | J8: FECHA FIN: | L8: 44925
J10: PRECIO VENTA (SIN IVA): | M10: =+N94 -> 97148.99 | N10: Euros
J11: ESFUERZO (TRABAJO): | M11: =+G31 -> 3212 | N11: Horas
J12: MARGEN BENEFICIOS: | M12: =100*(N94-N81)/N81 -> 27.137575 | N12: %
A14: 1. ESTIMACIÓN DE COSTES Y GASTOS
B16: 1.A | C16: PERSONAL
J17: PORCENTAJE DE COSTES INDIRECTOS (OVERHEAD) | N17: =+OVERHEAD!F3 -> 0.38795477
J18: COTIZACIÓN SEGURIDAD SOCIAL | N18: 0.3
J19: PORCENTAJE CONTINGENCIAS PARA PERSONAL | N19: 0.05
C21: PERSONAL | G21: HORAS TR. | H21: Coste Bruto / Hora | J21: Coste SS / Hora | L21: Contingen./H | M21: Total / Hora | N21: COSTE FINAL
C22: Analista | G22: 710 | H22: =30000/1760 -> 17.045455 | J22: =+H22*$N$18 -> 5.1136364 | L22: =+(H22+J22)*$N$19 -> 1.1079545 | M22: =+L22+J22+H22 -> 23.267045 | N22: =+M22*G22 -> 16519.602
C23: Diseñador Gráfico Aplicativos | G23: 100 | H23: =20000/1760 -> 11.363636 | J23: =+H23*$N$18 -> 3.4090909 | L23: =+(H23+J23)*$N$19 -> 0.73863636 | M23: =+L23+J23+H23 -> 15.511364 | N23: =+M23*G23 -> 1551.1364
C24: Jefe de Proyecto | G24: 250 | H24: =40000/1760 -> 22.727273 | J24: =+H24*$N$18 -> 6.8181818 | L24: =+(H24+J24)*$N$19 -> 1.4772727 | M24: =+L24+J24+H24 -> 31.022727 | N24: =+M24*G24 -> 7755.6818
C25: Programador | G25: 1720 | H25: =22500/1760 -> 12.784091 | J25: =+H25*$N$18 -> 3.8352273 | L25: =+(H25+J25)*$N$19 -> 0.83096591 | M25: =+L25+J25+H25 -> 17.450284 | N25: =+M25*G25 -> 30014.489
C26: Supervisor calidad aplicativos | G26: 232 | H26: =35000/1760 -> 19.886364 | J26: =+H26*$N$18 -> 5.9659091 | L26: =+(H26+J26)*$N$19 -> 1.2926136 | M26: =+L26+J26+H26 -> 27.144886 | N26: =+M26*G26 -> 6297.6136
C27: Técnico de bases de datos | G27: 100 | H27: =32000/1760 -> 18.181818 | J27: =+H27*$N$18 -> 5.4545455 | L27: =+(H27+J27)*$N$19 -> 1.1818182 | M27: =+L27+J27+H27 -> 24.818182 | N27: =+M27*G27 -> 2481.8182
C28: Técnico de sistemas | G28: 100 | H28: =32000/1760 -> 18.181818 | J28: =+H28*$N$18 -> 5.4545455 | L28: =+(H28+J28)*$N$19 -> 1.1818182 | M28: =+L28+J28+H28 -> 24.818182 | N28: =+M28*G28 -> 2481.8182
C29: [Insertar más líneas aquí] | J29: =+H29*$N$18 -> 0 | L29: =+(H29+J29)*$N$19 -> 0 | M29: =+L29+J29+H29 -> 0 | N29: =+M29*G29 -> 0
C31: HORAS TOTALES | G31: =SUM(G22:G29) -> 3212 | K31: SUBTOTAL PERSONAL | N31: =SUM(N22:N29) -> 67102.159
B33: 1.B | C33: SUBCONTRATACIONES
I34: PORCENTAJE CONTINGENCIAS PARA SUBCONTRATACION
C36: EMPRESA | E36: DESCRIPCIÓN | I36: UNIDADES | J36: COSTE/U | L36: CONTING. | M36: TOTAL/U | N36: COSTE FINAL
C37: 3D Designs S.L | E37: 2150 | L37: =+J37*$N$34 -> 0 | M37: =+L37+J37 -> 0 | N37: =+I37*M37 -> 0
C38: Telefónica | E38: 49€ + 29/mes | L38: =+J38*$N$34 -> 0 | M38: =+L38+J38 -> 0 | N38: =+I38*M38 -> 0
L39: =+J39*$N$34 -> 0 | M39: =+L39+J39 -> 0 | N39: =+I39*M39 -> 0
C40: [Insertar más líneas aquí] | L40: =+J40*$N$34 -> 0 | M40: =+L40+J40 -> 0 | N40: =+I40*M40 -> 0
K42: SUBTOTAL SUBCONTRATACIÓN | N42: =SUM(N37:N40) -> 0
B44: 1.C | C44: EQUIPAMIENTO
J45: PORCENTAJE CONTINGENCIAS PARA EQUIPAMIENTO | N45: 0.02
C47: EQUIPO | E47: DESCRIPCIÓN (opcional) | I47: UNIDADES | J47: COSTE/U | L47: CONTING. | M47: TOTAL/U | N47: COSTE FINAL
C48: HW-SERV | E48: Tipo hardware, IBM | I48: 1 | J48: 4800 | L48: =+J48*$N$45 -> 96 | M48: =+L48+J48 -> 4896 | N48: =+M48*I48 -> 4896
C49: SW-SERV | E49: Tipo software, redhat | I49: 1 | J49: 250 | L49: =+J49*$N$45 -> 5 | M49: =+L49+J49 -> 255 | N49: =+M49*I49 -> 255
L50: =+J50*$N$45 -> 0 | M50: =+L50+J50 -> 0 | N50: =+M50*I50 -> 0
C51: [Insertar más líneas aquí] | L51: =+J51*$N$45 -> 0 | M51: =+L51+J51 -> 0 | N51: =+M51*I51 -> 0
K53: SUBTOTAL EQUIPAMIENTO | N53: =SUM(N48:N51) -> 5151
B55: 1.D | C55: AMORTIZACION HW/SW
C57: REFERENCIA | D57: TIPO | E57: PRECIO/UD | F57: F. COMPRA | G57: FIN AMOR | H57: UNIDADES | I57: COST Ud/D | J57: F. INI USO | K57: F. FIN USO | L57: DIAS USO | M57: % USO | N57: COSTE FINAL
C58: DES1 | D58: PC | E58: 850 | F58: 43831 | G58: 44927 | H58: 2 | I58: =IF(OR(F58="",G58=""),0,E58/DAYS360(F58,G58,TRUE())) -> 0.78703704 | J58: 44562 | K58: 44927 | L58: =IF(J58>=G58,0,DAYS360(MAX(F58,J58),MIN(G58,K58),TRUE())) -> 360 | M58: 1 | N58: =+L58*I58*H58*M58 -> 566.66667
C59: DES2 | D59: PC | E59: 1200 | F59: 44348 | G59: 45444 | H59: 2 | I59: =IF(OR(F59="",G59=""),0,E59/DAYS360(F59,G59,TRUE())) -> 1.1111111 | J59: 44562 | K59: 44927 | L59: =IF(J59>=G59,0,DAYS360(MAX(F59,J59),MIN(G59,K59),TRUE())) -> 360 | M59: 1 | N59: =+L59*I59*H59*M59 -> 800
C60: SERV1 | D60: SERVIDOR | E60: 4800 | F60: 43252 | G60: 45078 | H60: 1 | I60: =IF(OR(F60="",G60=""),0,E60/DAYS360(F60,G60,TRUE())) -> 2.6666667 | J60: 44608 | K60: 44866 | L60: =IF(J60>=G60,0,DAYS360(MAX(F60,J60),MIN(G60,K60),TRUE())) -> 255 | M60: 0.2 | N60: =+L60*I60*H60*M60 -> 136
C61: TAB1 | D61: TABLET | E61: 600 | F61: 44075 | G61: 44805 | H61: 1 | I61: =IF(OR(F61="",G61=""),0,E61/DAYS360(F61,G61,TRUE())) -> 0.83333333 | J61: 44866 | K61: 44927 | L61: =IF(J61>=G61,0,DAYS360(MAX(F61,J61),MIN(G61,K61),TRUE())) -> 0 | M61: 1 | N61: =+L61*I61*H61*M61 -> 0
C62: MIND445 | D62: SW | E62: 400 | F62: 43132 | G62: 44593 | H62: 1 | I62: =IF(OR(F62="",G62=""),0,E62/DAYS360(F62,G62,TRUE())) -> 0.27777778 | J62: 44562 | K62: 44682 | L62: =IF(J62>=G62,0,DAYS360(MAX(F62,J62),MIN(G62,K62),TRUE())) -> 30 | M62: 1 | N62: =+L62*I62*H62*M62 -> 8.3333333
C63: DWCS6 | D63: SW | E63: 500 | F63: 42826 | G63: 44287 | H63: 3 | I63: =IF(OR(F63="",G63=""),0,E63/DAYS360(F63,G63,TRUE())) -> 0.34722222 | J63: 44608 | K63: 44927 | L63: =IF(J63>=G63,0,DAYS360(MAX(F63,J63),MIN(G63,K63),TRUE())) -> 0 | M63: 1 | N63: =+L63*I63*H63*M63 -> 0
C64: MVS2010 | D64: SW | E64: 2500 | F64: 44075 | G64: 45536 | H64: 2 | I64: =IF(OR(F64="",G64=""),0,E64/DAYS360(F64,G64,TRUE())) -> 1.7361111 | J64: 44682 | K64: 44927 | L64: =IF(J64>=G64,0,DAYS360(MAX(F64,J64),MIN(G64,K64),TRUE())) -> 240 | M64: 1 | N64: =+L64*I64*H64*M64 -> 833.33333
C65: [Insertar] | I65: =IF(OR(F65="",G65=""),0,E65/DAYS360(F65,G65,TRUE())) -> 0 | L65: =IF(J65>=G65,0,DAYS360(MAX(F65,J65),MIN(G65,K65),TRUE())) -> 0 | N65: =+L65*I65*H65*M65 -> 0
K67: SUBTOTAL AMORTIZACIÓN | N67: =SUM(N58:N65) -> 2344.3333
B69: 1.E | C69: OTROS GASTOS
J70: PORCENTAJE DE CONTINGENCIAS OTROS GASTOS | N70: 0.1
C72: DESCRIPCIÓN DEL GASTO | K72: UNIDADES | L72: COSTE / Ud. | M72: CONTING. | N72: COSTE FINAL
C73: MATERIAL FUNGIBLE | K73: 3 | L73: 100 | M73: =L73*$N$70 -> 10 | N73: =+K73*(L73+M73) -> 330
C74: MATERIAL FUNGIBLE RESTO | K74: 9 | L74: 50 | M74: =L74*$N$70 -> 5 | N74: =+K74*(L74+M74) -> 495
C75: VIAJES | K75: 6 | L75: 150 | M75: =L75*$N$70 -> 15 | N75: =+K75*(L75+M75) -> 990
M76: =L76*$N$70 -> 0 | N76: =+K76*(L76+M76) -> 0
C77: [Insertar más líneas aquí] | M77: =L77*$N$70 -> 0 | N77: =+K77*(L77+M77) -> 0
K79: SUBTOTAL AMORTIZACIÓN | N79: =SUM(N73:N77) -> 1815
B81: TOTAL COSTES | N81: =+N79+N67+N53+N42+N31 -> 76412.492
A83: 2. PRECIO DE VENTA
B85: 2.A | C85: MARGEN DE BENEFICIOS POR CONCEPTOS
C87: CONCEPTO | K87: GASTOS | L87: % MARGEN | M87: BENEFICIO | N87: TOTAL
C88: =+C16 -> PERSONAL | K88: =+N31 -> 67102.159 | L88: 0.3 | M88: =+K88*L88 -> 20130.648 | N88: =+K88+M88 -> 87232.807
C89: =+C33 -> SUBCONTRATACIONES | K89: =+N42 -> 0 | L89: 0.15 | M89: =+K89*L89 -> 0 | N89: =+K89+M89 -> 0
C90: =+C44 -> EQUIPAMIENTO | K90: =+N53 -> 5151 | L90: 0.1 | M90: =+K90*L90 -> 515.1 | N90: =+K90+M90 -> 5666.1
C91: =+C55 -> AMORTIZACION HW/SW | K91: =+N67 -> 2344.3333 | L91: 0 | M91: =+K91*L91 -> 0 | N91: =+K91+M91 -> 2344.3333
C92: =+C69 -> OTROS GASTOS | K92: =+N79 -> 1815 | L92: 0.05 | M92: =+K92*L92 -> 90.75 | N92: =+K92+M92 -> 1905.75
C94: PORCENTAJE MARGEN PROYECTO Y PRECIO FINAL (IVA no incluido) | M94: =SUM(M88:M92) -> 20736.498 | N94: =SUM(N88:N92) -> 97148.99
B96: 2.B | C96: PRECIO DE VENTA
C98: PRECIO DE VENTA (IVA incluido) | K98: IVA | L98: =+N94*0.21 -> 20401.288 | M98: TOTAL | N98: =+N94+L98 -> 117550.28

Sheet PLAN FINANCIERO
A1: PLAN FINANCIERO DEL PROYECTO
A3: DATOS DEL PROYECTO
A5: TITULO: | C5: =IF(ESTIMACION!C5="","N/A",ESTIMACION!C5) -> DESARROLLO DE UN PORTAL WEB | I5: REFERENCIA: | K5: =IF(ESTIMACION!L5="","N/A",ESTIMACION!L5) -> DES-01-2022
A6: CLIENTE: | C6: =IF(ESTIMACION!C6="","N/A",ESTIMACION!C6) -> MEDIOLADO | I6: RESPONSABLE: | K6: =IF(ESTIMACION!L6="","N/A",ESTIMACION!L6) -> PABLO Y CAMILO
A8: FECHA INICIO: | D8: =IF(ESTIMACION!C8="","N/A",ESTIMACION!C8) -> 44562 | I8: FECHA FIN: | K8: =IF(ESTIMACION!L8="","N/A",ESTIMACION!L8) -> 44925
A10: FECHA INFORME : | D10: 44699 | I10: PRECIO VENTA (SIN IVA): | L10: =+ESTIMACION!M10 -> 97148.99 | N10: Euros
I11: ESFUERZO: | L11: =+ESTIMACION!M11 -> 3212 | N11: Horas
I12: MARGEN BENEFICIOS: | L12: =+ESTIMACION!M12 -> 27.137575 | N12: %
I14: TIPO INTERES ANUAL : | M14: 0.02
I15: COSTE DE OPORTUNIDAD ANUAL : | M15: 0.08
A17: 1. PROYECCION TEMPORAL DE COSTES Y GASTOS :
D19: DISTRIBUCION HORAS DE TRABAJO | Q19: TOTAL PREVISTO
A20: PERSONAL | D20: MES 1 | E20: MES 2 | F20: MES 3 | G20: MES 4 | H20: MES 5 | I20: MES 6 | J20: MES 7 | K20: MES 8 | L20: MES 9 | M20: MES 10 | N20: MES 11 | O20: MES 12 | P20: <INSER> | Q20: PLAN_F | R20: ESTIMADO
A21: =+ESTIMACION!C22 -> Analista | D21: =200*2/3 -> 133.33333 | E21: =200/3 + 250/5 -> 116.66667 | F21: =250*2/5 -> 100 | G21: =250*2/5 -> 100 | H21: =180/6 -> 30 | I21: =180/6 -> 30 | J21: =180/6 -> 30 | K21: =180/6 -> 30 | L21: =180/6 -> 30 | M21: =180/6 -> 30 | N21: =80/2 -> 40 | O21: =80/2 -> 40 | Q21: =SUM(D21:P21) -> 710 | R21: =+ESTIMACION!G22 -> 710
A22: =+ESTIMACION!C23 -> Diseñador Gráfico Aplicativos | D22: 0 | E22: 20 | F22: =100*2/5 -> 40 | G22: =100*2/5 -> 40 | H22: 0 | I22: 0 | J22: 0 | K22: 0 | L22: 0 | M22: 0 | N22: 0 | O22: 0 | Q22: =SUM(D22:P22) -> 100 | R22: =+ESTIMACION!G23 -> 100
A23: =+ESTIMACION!C24 -> Jefe de Proyecto | D23: =40*2/3 -> 26.666667 | E23: =40/3 + 40/5 -> 21.333333 | F23: =40*2/5 -> 16 | G23: =40*2/5 -> 16 | H23: =90/6 -> 15 | I23: =90/6 -> 15 | J23: =90/6 -> 15 | K23: =90/6 -> 15 | L23: =90/6 -> 15 | M23: =90/6 -> 15 | N23: =80/2 -> 40 | O23: =80/2 -> 40 | Q23: =SUM(D23:P23) -> 250 | R23: =+ESTIMACION!G24 -> 250
A24: =+ESTIMACION!C25 -> Programador | D24: 0 | E24: =100/5 -> 20 | F24: =100*2/5 -> 40 | G24: =100*2/5 -> 40 | H24: =1500/6 -> 250 | I24: =1500/6 -> 250 | J24: =1500/6 -> 250 | K24: =1500/6 -> 250 | L24: =1500/6 -> 250 | M24: =1500/6 -> 250 | N24: =120/2 -> 60 | O24: =120/2 -> 60 | Q24: =SUM(D24:P24) -> 1720 | R24: =+ESTIMACION!G25 -> 1720
A25: =+ESTIMACION!C26 -> Supervisor calidad aplicativos | D25: =20*2/3 -> 13.333333 | E25: =20/3 + 30/5 -> 12.666667 | F25: =30*2/5 -> 12 | G25: =30*2/5 -> 12 | H25: =102/6 -> 17 | I25: =102/6 -> 17 | J25: =102/6 -> 17 | K25: =102/6 -> 17 | L25: =102/6 -> 17 | M25: =102/6 -> 17 | N25: =80/2 -> 40 | O25: =80/2 -> 40 | Q25: =SUM(D25:P25) -> 232 | R25: =+ESTIMACION!G26 -> 232
A26: =+ESTIMACION!C27 -> Técnico de bases de datos | D26: =60*2/3 -> 40 | E26: =60/3 -> 20 | F26: 0 | G26: 0 | H26: 0 | I26: 0 | J26: 0 | K26: 0 | L26: 0 | M26: 0 | N26: =40/2 -> 20 | O26: =40/2 -> 20 | Q26: =SUM(D26:P26) -> 100 | R26: =+ESTIMACION!G27 -> 100
A27: =+ESTIMACION!C28 -> Técnico de sistemas | D27: 0 | E27: =60/5 -> 12 | F27: =60*2/5 -> 24 | G27: =60*2/5 -> 24 | H27: 0 | I27: 0 | J27: 0 | K27: 0 | L27: 0 | M27: 0 | N27: =40/2 -> 20 | O27: =40/2 -> 20 | Q27: =SUM(D27:P27) -> 100 | R27: =+ESTIMACION!G28 -> 100
A28: =+ESTIMACION!C29 -> [Insertar más líneas aquí] | Q28: =SUM(D28:P28) -> 0 | R28: =+ESTIMACION!G29 -> 0
A30: COSTE PERSONAL | D30: =SUMPRODUCT(ESTIMACION!$M$22:$M$29,'PLAN FINANCIERO'!D21:D28) -> 5284.2045 | E30: =SUMPRODUCT(ESTIMACION!$M$22:$M$29,'PLAN FINANCIERO'!E21:E28) -> 5173.5568 | F30: =SUMPRODUCT(ESTIMACION!$M$22:$M$29,'PLAN FINANCIERO'!F21:F28) -> 5062.9091 | G30: =SUMPRODUCT(ESTIMACION!$M$22:$M$29,'PLAN FINANCIERO'!G21:G28) -> 5062.9091 | H30: =SUMPRODUCT(ESTIMACION!$M$22:$M$29,'PLAN FINANCIERO'!H21:H28) -> 5987.3864 | I30: =SUMPRODUCT(ESTIMACION!$M$22:$M$29,'PLAN FINANCIERO'!I21:I28) -> 5987.3864 | J30: =SUMPRODUCT(ESTIMACION!$M$22:$M$29,'PLAN FINANCIERO'!J21:J28) -> 5987.3864 | K30: =SUMPRODUCT(ESTIMACION!$M$22:$M$29,'PLAN FINANCIERO'!K21:K28) -> 5987.3864 | ... P30: =SUMPRODUCT(ESTIMACION!$M$22:$M$29,'PLAN FINANCIERO'!P21:P28) -> 0 | Q30: =SUM(D30:P30) -> 67102.159 | R30: =+ESTIMACION!N31 -> 67102.159
D33: DISTRIBUCION HORAS DE TRABAJO | Q33: TOTAL PREVISTO
A34: =+ESTIMACION!C33 -> SUBCONTRATACIONES | D34: MES 1 | E34: MES 2 | F34: MES 3 | G34: MES 4 | H34: MES 5 | I34: MES 6 | J34: MES 7 | K34: MES 8 | L34: MES 9 | M34: MES 10 | N34: MES 11 | O34: MES 12 | P34: <INSER> | Q34: PLAN_F | R34: ESTIMADO
A35: =+ESTIMACION!C37 -> 3D Designs S.L | Q35: =SUM(D35:P35) -> 0 | R35: =+ESTIMACION!N37 -> 0
A36: =+ESTIMACION!C38 -> Telefónica | Q36: =SUM(D36:P36) -> 0 | R36: =+ESTIMACION!N38 -> 0
A37: =+ESTIMACION!C39 -> 0 | Q37: =SUM(D37:P37) -> 0 | R37: =+ESTIMACION!N39 -> 0
A38: =+ESTIMACION!C40 -> [Insertar más líneas aquí] | Q38: =SUM(D38:P38) -> 0 | R38: =+ESTIMACION!N40 -> 0
A40: COSTE SUBCONTRATACION | D40: =SUM(D35:D38) -> 0 | E40: =SUM(E35:E38) -> 0 | F40: =SUM(F35:F38) -> 0 | G40: =SUM(G35:G38) -> 0 | H40: =SUM(H35:H38) -> 0 | I40: =SUM(I35:I38) -> 0 | J40: =SUM(J35:J38) -> 0 | K40: =SUM(K35:K38) -> 0 | ... O40: =SUM(O35:O38) -> 0 | P40: =SUMPRODUCT(ESTIMACION!$M$22:$M$29,'PLAN FINANCIERO'!P30:P38) -> #VALUE! | Q40: =SUM(D40:P40) -> #VALUE! | R40: =SUM(R35:R38) -> 0
D43: DISTRIBUCION HORAS DE TRABAJO | Q43: TOTAL PREVISTO
A44: =+ESTIMACION!C44 -> EQUIPAMIENTO | D44: MES 1 | E44: MES 2 | F44: MES 3 | G44: MES 4 | H44: MES 5 | I44: MES 6 | J44: MES 7 | K44: MES 8 | L44: MES 9 | M44: MES 10 | N44: MES 11 | O44: MES 12 | P44: <INSER> | Q44: PLAN_F | R44: ESTIMADO
A45: =+ESTIMACION!C48 -> HW-SERV | D45: 0 | E45: 0 | F45: 0 | G45: 0 | H45: 0 | I45: 0 | J45: 0 | K45: 0 | L45: 0 | M45: =4800+ 0.02*4800 -> 4896 | N45: 0 | O45: 0 | Q45: =SUM(D45:P45) -> 4896 | R45: =+ESTIMACION!N48 -> 4896
A46: =+ESTIMACION!C49 -> SW-SERV | D46: 0 | E46: 0 | F46: 0 | G46: 0 | H46: 0 | I46: 0 | J46: 0 | K46: 0 | L46: 0 | M46: =250+0.02*250 -> 255 | N46: 0 | O46: 0 | Q46: =SUM(D46:P46) -> 255 | R46: =+ESTIMACION!N49 -> 255
A47: =+ESTIMACION!C50 -> 0 | Q47: =SUM(D47:P47) -> 0 | R47: =+ESTIMACION!N50 -> 0
A48: =+ESTIMACION!C51 -> [Insertar más líneas aquí] | Q48: =SUM(D48:P48) -> 0 | R48: =+ESTIMACION!N51 -> 0
A50: COSTE EQUIPAMIENTO | D50: =SUM(D45:D48) -> 0 | E50: =SUM(E45:E48) -> 0 | F50: =SUM(F45:F48) -> 0 | G50: =SUM(G45:G48) -> 0 | H50: =SUM(H45:H48) -> 0 | I50: =SUM(I45:I48) -> 0 | J50: =SUM(J45:J48) -> 0 | K50: =SUM(K45:K48) -> 0 | ... O50: =SUM(O45:O48) -> 0 | Q50: =SUM(D50:P50) -> 5151 | R50: =SUM(R45:R48) -> 5151
D53: DISTRIBUCION HORAS DE TRABAJO | Q53: TOTAL PREVISTO
A54: =+ESTIMACION!C69 -> OTROS GASTOS | D54: MES 1 | E54: MES 2 | F54: MES 3 | G54: MES 4 | H54: MES 5 | I54: MES 6 | J54: MES 7 | K54: MES 8 | L54: MES 9 | M54: MES 10 | N54: MES 11 | O54: MES 12 | P54: <INSER> | Q54: PLAN_F | R54: ESTIMADO
A55: =+ESTIMACION!C73 -> MATERIAL FUNGIBLE | D55: 110 | E55: 110 | F55: 110 | Q55: =SUM(D55:P55) -> 330 | R55: =+ESTIMACION!N73 -> 330
A56: =+ESTIMACION!C74 -> MATERIAL FUNGIBLE RESTO | G56: 55 | H56: 55 | I56: 55 | J56: 55 | K56: 55 | L56: 55 | M56: 55 | N56: 55 | O56: 55 | Q56: =SUM(D56:P56) -> 495 | R56: =+ESTIMACION!N74 -> 495
A57: =+ESTIMACION!C75 -> VIAJES | D57: 165 | F57: 165 | H57: 165 | J57: 165 | L57: 165 | N57: 165 | Q57: =SUM(D57:P57) -> 990 | R57: =+ESTIMACION!N75 -> 990
A58: =+ESTIMACION!C76 -> 0 | Q58: =SUM(D58:P58) -> 0 | R58: =+ESTIMACION!N76 -> 0
A60: COSTE EQUIPAMIENTO | D60: =SUM(D55:D58) -> 275 | E60: =SUM(E55:E58) -> 110 | F60: =SUM(F55:F58) -> 275 | G60: =SUM(G55:G58) -> 55 | H60: =SUM(H55:H58) -> 220 | I60: =SUM(I55:I58) -> 55 | J60: =SUM(J55:J58) -> 220 | K60: =SUM(K55:K58) -> 55 | ... O60: =SUM(O55:O58) -> 55 | P60: =SUMPRODUCT(ESTIMACION!$M$22:$M$29,'PLAN FINANCIERO'!P51:P58) -> 0 | Q60: =SUM(D60:P60) -> 1815 | R60: =SUM(R55:R58) -> 1815
D63: RESUMEN DE PREVISION DE GASTOS, COSTES | Q63: TOTAL PREVISTO
B64: CONCEPTO | D64: MES 1 | E64: MES 2 | F64: MES 3 | G64: MES 4 | H64: MES 5 | I64: MES 6 | J64: MES 7 | K64: MES 8 | L64: MES 9 | M64: MES 10 | N64: MES 11 | O64: MES 12 | P64: <INSER> | Q64: PLAN_F | R64: ESTIMADO
B65: =+ESTIMACION!C16 -> PERSONAL | D65: =SUMPRODUCT(ESTIMACION!$M$22:$M$29,'PLAN FINANCIERO'!D21:D28) -> 5284.2045 | E65: =SUMPRODUCT(ESTIMACION!$M$22:$M$29,'PLAN FINANCIERO'!E21:E28) -> 5173.5568 | F65: =SUMPRODUCT(ESTIMACION!$M$22:$M$29,'PLAN FINANCIERO'!F21:F28) -> 5062.9091 | G65: =SUMPRODUCT(ESTIMACION!$M$22:$M$29,'PLAN FINANCIERO'!G21:G28) -> 5062.9091 | H65: =SUMPRODUCT(ESTIMACION!$M$22:$M$29,'PLAN FINANCIERO'!H21:H28) -> 5987.3864 | I65: =SUMPRODUCT(ESTIMACION!$M$22:$M$29,'PLAN FINANCIERO'!I21:I28) -> 5987.3864 | J65: =SUMPRODUCT(ESTIMACION!$M$22:$M$29,'PLAN FINANCIERO'!J21:J28) -> 5987.3864 | K65: =SUMPRODUCT(ESTIMACION!$M$22:$M$29,'PLAN FINANCIERO'!K21:K28) -> 5987.3864 | ... O65: =SUMPRODUCT(ESTIMACION!$M$22:$M$29,'PLAN FINANCIERO'!O21:O28) -> 5297.1307 | Q65: =SUM(D65:P65) -> 67102.159 | R65: =SUMPRODUCT(ESTIMACION!$M$22:$M$29,'PLAN FINANCIERO'!R21:R28) -> 67102.159
B66: =+ESTIMACION!C33 -> SUBCONTRATACIONES | D66: =+D40 -> 0 | E66: =+E40 -> 0 | F66: =+F40 -> 0 | G66: =+G40 -> 0 | H66: =+H40 -> 0 | I66: =+I40 -> 0 | J66: =+J40 -> 0 | K66: =+K40 -> 0 | ... O66: =+O40 -> 0 | Q66: =SUM(D66:P66) -> 0 | R66: =+ESTIMACION!N42 -> 0
B67: =+ESTIMACION!C44 -> EQUIPAMIENTO | D67: =+D50 -> 0 | E67: =+E50 -> 0 | F67: =+F50 -> 0 | G67: =+G50 -> 0 | H67: =+H50 -> 0 | I67: =+I50 -> 0 | J67: =+J50 -> 0 | K67: =+K50 -> 0 | ... O67: =+O50 -> 0 | Q67: =SUM(D67:P67) -> 5151 | R67: =+ESTIMACION!N53 -> 5151
B68: =+ESTIMACION!C69 -> OTROS GASTOS | D68: =+D60 -> 275 | E68: =+E60 -> 110 | F68: =+F60 -> 275 | G68: =+G60 -> 55 | H68: =+H60 -> 220 | I68: =+I60 -> 55 | J68: =+J60 -> 220 | K68: =+K60 -> 55 | ... O68: =+O60 -> 55 | Q68: =SUM(D68:P68) -> 1815 | R68: =+ESTIMACION!N79 -> 1815
B70: TOTAL COSTES | D70: =SUM(D65:D68) -> 5559.2045 | E70: =SUM(E65:E68) -> 5283.5568 | F70: =SUM(F65:F68) -> 5337.9091 | G70: =SUM(G65:G68) -> 5117.9091 | H70: =SUM(H65:H68) -> 6207.3864 | I70: =SUM(I65:I68) -> 6042.3864 | J70: =SUM(J65:J68) -> 6207.3864 | K70: =SUM(K65:K68) -> 6042.3864 | ... R70: =SUM(R65:R68) -> 74068.159
B71: COSTE ACUMULADO | D71: =+D70 -> 5559.2045 | E71: =+D71+E70 -> 10842.761 | F71: =+E71+F70 -> 16180.67 | G71: =+F71+G70 -> 21298.58 | H71: =+G71+H70 -> 27505.966 | I71: =+H71+I70 -> 33548.352 | J71: =+I71+J70 -> 39755.739 | K71: =+J71+K70 -> 45798.125 | L71: =+K71+L70 -> 52005.511 | ... P71: =+O71+P70 -> 74068.159
A73: 2. INGRESOS
D75: PREVISION DE GASTOS, COSTES E INGRESOS | Q75: TOTAL PREVISTO
B76: CONCEPTO | D76: MES 1 | E76: MES 2 | F76: MES 3 | G76: MES 4 | H76: MES 5 | I76: MES 6 | J76: MES 7 | K76: MES 8 | L76: MES 9 | M76: MES 10 | N76: MES 11 | O76: MES 12 | P76: <INSER> | Q76: PLAN_F | R76: ESTIMADO
B77: INGRESOS | D77: =R77*0.2 -> 19429.798 | I77: =R77*0.2 -> 19429.798 | O77: =R77*0.6 -> 58289.394 | Q77: =SUM(D77:P77) -> 97148.99 | R77: =+ESTIMACION!N94 -> 97148.99
B78: INGRESOS ACUMULADO | D78: =+D77 -> 19429.798 | E78: =+D78+E77 -> 19429.798 | F78: =+E78+F77 -> 19429.798 | G78: =+F78+G77 -> 19429.798 | H78: =+G78+H77 -> 19429.798 | I78: =+H78+I77 -> 38859.596 | J78: =+I78+J77 -> 38859.596 | K78: =+J78+K77 -> 38859.596 | L78: =+K78+L77 -> 38859.596 | ... P78: =+O78+P77 -> 97148.99
A81: 3. RESULTADOS
D83: MESES
B84: CONCEPTO | D84: 1 | E84: 2 | F84: 3 | G84: 4 | H84: 5 | I84: 6 | J84: 7 | K84: 8 | L84: 9 | M84: 10 | N84: 11 | O84: 12 | P84: 13 | Q84: PLAN_F | R84: ESTIMADO
B85: BENEFICIO CONTABLE | D85: =+D77-D70 -> 13870.593 | E85: =+E77-E70 -> -5283.5568 | F85: =+F77-F70 -> -5337.9091 | G85: =+G77-G70 -> -5117.9091 | H85: =+H77-H70 -> -6207.3864 | I85: =+I77-I70 -> 13387.412 | J85: =+J77-J70 -> -6207.3864 | K85: =+K77-K70 -> -6042.3864 | ... P85: =+P77-P70 -> 0 | Q85: =SUM(D85:P85) -> 23080.831 | R85: =+ESTIMACION!M94+ESTIMACION!K91 -> 23080.831
B86: MARGEN ACUMULADO | D86: =+D85 -> 13870.593 | E86: =+D86+E85 -> 8587.0367 | F86: =+E86+F85 -> 3249.1276 | G86: =+F86+G85 -> -1868.7815 | H86: =+G86+H85 -> -8076.1679 | I86: =+H86+I85 -> 5311.2438 | J86: =+I86+J85 -> -896.14258 | K86: =+J86+K85 -> -6938.5289 | L86: =+K86+L85 -> -13145.915 | ... P86: =+O86+P85 -> 23080.831
B87: VAN | D87: =+D85/(1+$F$90)^D84 -> 13781.92 | E87: =+E85/(1+$F$90)^E84 -> -5216.2183 | F87: =+F85/(1+$F$90)^F84 -> -5236.188 | G87: =+G85/(1+$F$90)^G84 -> -4988.2857 | H87: =+H85/(1+$F$90)^H84 -> -6011.4912 | I87: =+I85/(1+$F$90)^I84 -> 12882.043 | J87: =+J85/(1+$F$90)^J84 -> -5934.8751 | K87: =+K85/(1+$F$90)^K84 -> -5740.1863 | ... P87: =+P85/(1+$F$90)^P84 -> 0
B88: VAN ACUMULADO | D88: =+D87 -> 13781.92 | E88: =+D88+E87 -> 8565.7019 | F88: =+E88+F87 -> 3329.5139 | G88: =+F88+G87 -> -1658.7718 | H88: =+G88+H87 -> -7670.2629 | I88: =+H88+I87 -> 5211.7799 | J88: =+I88+J87 -> -723.0952 | K88: =+J88+K87 -> -6463.2815 | L88: =+K88+L87 -> -12322.517 | ... O88: =+N88+O87 -> 21054.102 | P88: =+P87 -> 0
B90: TASA MENSUAL COSTE OPORTUNIDAD | F90: =+POWER((1+M15),(30/360))-1 -> 0.0064340301
B93: Conversión de la tasa anual a tasa mensual: | F93: IPV=(1+%)Elevado(30/360) - 1
C95: Tasa anual | D95: 0 | F95: Tasa mensual | H95: =POWER((1+D95),(30/360))-1 -> 0
C96: Tasa mensual | D96: 0 | F96: Tasa anual | H96: =POWER((1+D96),(360/30))-1 -> 0

Sheet INDICADORES
A1: INDICADORES ECONÓMICOS Y FINANCIEROS DEL PROYECTO
A3: DATOS DEL PROYECTO
A5: TITULO: | C5: =IF(ESTIMACION!C5="","N/A",ESTIMACION!C5) -> DESARROLLO DE UN PORTAL WEB | I5: REFERENCIA: | K5: =IF(ESTIMACION!L5="","N/A",ESTIMACION!L5) -> DES-01-2022
A6: CLIENTE: | C6: =IF(ESTIMACION!C6="","N/A",ESTIMACION!C6) -> MEDIOLADO | I6: RESPONSABLE: | K6: =IF(ESTIMACION!L6="","N/A",ESTIMACION!L6) -> PABLO Y CAMILO
A8: FECHA INICIO: | D8: =IF(ESTIMACION!C8="","N/A",ESTIMACION!C8) -> 44562 | I8: FECHA FIN: | K8: =IF(ESTIMACION!L8="","N/A",ESTIMACION!L8) -> 44925
A10: FECHA INFORME : | D10: =IF('PLAN FINANCIERO'!D10:F10="","N/A",'PLAN FINANCIERO'!D10:F10) -> 44699 | I10: PRECIO VENTA (SIN IVA): | L10: =+ESTIMACION!M10 -> 97148.99 | N10: Euros
I11: ESFUERZO: | L11: =+ESTIMACION!M11 -> 3212 | N11: Horas
I12: MARGEN BENEFICIOS: | L12: =+ESTIMACION!M12 -> 27.137575 | N12: %
I14: TIPO INTERES ANUAL : | M14: =+'PLAN FINANCIERO'!M14:N14 -> 0.02
I15: COSTE DE OPORTUNIDAD ANUAL : | M15: =+'PLAN FINANCIERO'!M15:N15 -> 0.08
I16: DURACIÓN (MESES):
A18: 1. PREVISIÓN DE CARGA DE TRABAJO (Histograma de recursos)
A42: 2. PREVISIÓN DE LA EVOLUCIÓN DE LOS DATOS ECONÓMICO-FINANCIEROS

Sheet CIERRE
A1: HOJA DE CIERRE ECONÓMICO DEL PROYECTO
A3: DATOS DEL PROYECTO
A5: TITULO: | C5: =IF(ESTIMACION!C5="","N/A",ESTIMACION!C5) -> DESARROLLO DE UN PORTAL WEB | I5: REFERENCIA: | K5: =IF(ESTIMACION!L5="","N/A",ESTIMACION!L5) -> DES-01-2022
A6: CLIENTE: | C6: =IF(ESTIMACION!C6="","N/A",ESTIMACION!C6) -> MEDIOLADO | I6: RESPONSABLE: | K6: =IF(ESTIMACION!L6="","N/A",ESTIMACION!L6) -> PABLO Y CAMILO
K8: PREVISTO | L8: REAL
A9: FECHA INFORME : | D9: 44699 | I9: PRECIO VENTA (SIN IVA): | K9: =+ESTIMACION!M10 -> 97148.99 | L9: =H82 -> 97148.99 | M9: Euros
I10: COSTE: | K10: =+ESTIMACION!N81 -> 76412.492 | L10: =SUM(H88:H92) -> 81360.694 | M10: Euros
I11: ESFUERZO: | K11: =+ESTIMACION!M11 -> 3212 | L11: =H30 -> 3312 | M11: Horas
I12: MARGEN BENEFICIOS: | K12: =+ESTIMACION!M12 -> 27.137575 | L12: =100*(L9-L10)/L10 -> 19.405311 | M12: %
I13: FECHA INICIO: | K13: =IF(ESTIMACION!C8="","N/A",ESTIMACION!C8) -> 44562 | L13: 44562 | M13: mes/año
I14: FECHA FIN: | K14: =IF(ESTIMACION!L8="","N/A",ESTIMACION!L8) -> 44925 | L14: 44925 | M14: mes/año
A16: 1. ESTIMACIÓN DE COSTES Y GASTOS
B18: 1.A | C18: PERSONAL
F19: TOTAL PREVISTO | H19: TOTAL FINAL | K19: DESVIACIÓN
C20: PERSONAL | F20: HORAS TR. | G20: COSTE | H20: HORAS TR. | I20: COSTE | J20: % | K20: HORAS TR. | L20: COSTE | M20: %
C21: =+ESTIMACION!C22 -> Analista | F21: =+ESTIMACION!G22 -> 710 | G21: =+ESTIMACION!N22 -> 16519.602 | H21: 730 | I21: =+H21*ESTIMACION!M22 -> 16984.943 | J21: =+IF(F21=0,"N/A",H21/F21) -> 1.028169 | K21: =+H21-F21 -> 20 | L21: =+I21-G21 -> 465.34091 | M21: =IF(F21=0,"N/A",J21-1) -> 0.028169014
C22: =+ESTIMACION!C23 -> Diseñador Gráfico Aplicativos | F22: =+ESTIMACION!G23 -> 100 | G22: =+ESTIMACION!N23 -> 1551.1364 | H22: 20 | I22: =+H22*ESTIMACION!M23 -> 310.22727 | J22: =+IF(F22=0,"N/A",H22/F22) -> 0.2 | K22: =+H22-F22 -> -80 | L22: =+I22-G22 -> -1240.9091 | M22: =IF(F22=0,"N/A",J22-1) -> -0.8
C23: =+ESTIMACION!C24 -> Jefe de Proyecto | F23: =+ESTIMACION!G24 -> 250 | G23: =+ESTIMACION!N24 -> 7755.6818 | H23: 260 | I23: =+H23*ESTIMACION!M24 -> 8065.9091 | J23: =+IF(F23=0,"N/A",H23/F23) -> 1.04 | K23: =+H23-F23 -> 10 | L23: =+I23-G23 -> 310.22727 | M23: =IF(F23=0,"N/A",J23-1) -> 0.04
C24: =+ESTIMACION!C25 -> Programador | F24: =+ESTIMACION!G25 -> 1720 | G24: =+ESTIMACION!N25 -> 30014.489 | H24: 1870 | I24: =+H24*ESTIMACION!M25 -> 32632.031 | J24: =+IF(F24=0,"N/A",H24/F24) -> 1.0872093 | K24: =+H24-F24 -> 150 | L24: =+I24-G24 -> 2617.5426 | M24: =IF(F24=0,"N/A",J24-1) -> 0.087209302
C25: =+ESTIMACION!C26 -> Supervisor calidad aplicativos | F25: =+ESTIMACION!G26 -> 232 | G25: =+ESTIMACION!N26 -> 6297.6136 | H25: 232 | I25: =+H25*ESTIMACION!M26 -> 6297.6136 | J25: =+IF(F25=0,"N/A",H25/F25) -> 1 | K25: =+H25-F25 -> 0 | L25: =+I25-G25 -> 0 | M25: =IF(F25=0,"N/A",J25-1) -> 0
C26: =+ESTIMACION!C27 -> Técnico de bases de datos | F26: =+ESTIMACION!G27 -> 100 | G26: =+ESTIMACION!N27 -> 2481.8182 | H26: 100 | I26: =+H26*ESTIMACION!M27 -> 2481.8182 | J26: =+IF(F26=0,"N/A",H26/F26) -> 1 | K26: =+H26-F26 -> 0 | L26: =+I26-G26 -> 0 | M26: =IF(F26=0,"N/A",J26-1) -> 0
C27: =+ESTIMACION!C28 -> Técnico de sistemas | F27: =+ESTIMACION!G28 -> 100 | G27: =+ESTIMACION!N28 -> 2481.8182 | H27: 100 | I27: =+H27*ESTIMACION!M28 -> 2481.8182 | J27: =+IF(F27=0,"N/A",H27/F27) -> 1 | K27: =+H27-F27 -> 0 | L27: =+I27-G27 -> 0 | M27: =IF(F27=0,"N/A",J27-1) -> 0
C28: =+ESTIMACION!C29 -> [Insertar más líneas aquí] | F28: =+ESTIMACION!G29 -> 0 | G28: =+ESTIMACION!N29 -> 0 | I28: =+H28*ESTIMACION!J29 -> 0 | J28: =+IF(F28=0,"N/A",H28/F28) -> N/A | K28: =+H28-F28 -> 0 | L28: =+I28-G28 -> 0 | M28: =IF(F28=0,"N/A",J28-1) -> N/A
C30: SUBTOTAL | F30: =SUM(F21:F28) -> 3212 | G30: =SUM(G21:G28) -> 67102.159 | H30: =SUM(H21:H28) -> 3312 | I30: =SUM(I21:I28) -> 69254.361 | J30: =+IF(F30=0,"N/A",H30/F30) -> 1.0311333 | K30: =SUM(K21:K28) -> 100 | L30: =SUM(L21:L28) -> 2152.2017 | M30: =IF(F30=0,"N/A",J30-1) -> 0.03113325
B32: 1.B | C32: SUBCONTRATACIONES
F33: TOTAL PREVISTO | H33: TOTAL FINAL | K33: DESVIACIÓN
C34: EMPRESA | F34: COSTE | H34: COSTE | J34: % | K34: COSTE | M34: %
C35: =+ESTIMACION!C37 -> 3D Designs S.L | F35: =+ESTIMACION!N37 -> 0 | H35: 2150 | J35: =+IF(F35=0,"N/A",H35/F35) -> N/A | K35: =+H35-F35 -> 2150 | M35: =IF(F35=0,"N/A",J35-1) -> N/A
C36: =+ESTIMACION!C38 -> Telefónica | F36: =+ESTIMACION!N38 -> 0 | H36: =49 + 29 -> 78 | J36: =+IF(F36=0,"N/A",H36/F36) -> N/A | K36: =+H36-F36 -> 78 | M36: =IF(F36=0,"N/A",J36-1) -> N/A
C37: =+ESTIMACION!C39 -> 0 | F37: =+ESTIMACION!N39 -> 0 | J37: =+IF(F37=0,"N/A",H37/F37) -> N/A | K37: =+H37-F37 -> 0 | M37: =IF(F37=0,"N/A",J37-1) -> N/A
C38: =+ESTIMACION!C40 -> [Insertar más líneas aquí] | F38: =+ESTIMACION!N40 -> 0 | J38: =+IF(F38=0,"N/A",H38/F38) -> N/A | K38: =+H38-F38 -> 0 | M38: =IF(F38=0,"N/A",J38-1) -> N/A
C40: SUBTOTAL | F40: =SUM(F35:F38) -> 0 | H40: =SUM(H35:H38) -> 2228 | J40: =+IF(F40=0,"N/A",H40/F40) -> N/A | K40: =SUM(K35:K38) -> 2228 | M40: =IF(F40=0,"N/A",J40-1) -> N/A
B43: 1.C | C43: EQUIPAMIENTO
F44: TOTAL PREVISTO | H44: TOTAL FINAL | K44: DESVIACIÓN
C45: EQUIPO | F45: COSTE | H45: COSTE | J45: % | K45: COSTE | M45: %
C46: =+ESTIMACION!C48 -> HW-SERV | F46: =+ESTIMACION!N48 -> 4896 | H46: 4700 | J46: =+IF(F46=0,"N/A",H46/F46) -> 0.95996732 | K46: =+H46-F46 -> -196 | M46: =IF(F46=0,"N/A",J46-1) -> -0.04003268
C47: =+ESTIMACION!C49 -> SW-SERV | F47: =+ESTIMACION!N49 -> 255 | H47: 399 | J47: =+IF(F47=0,"N/A",H47/F47) -> 1.5647059 | K47: =+H47-F47 -> 144 | M47: =IF(F47=0,"N/A",J47-1) -> 0.56470588
C48: =+ESTIMACION!C50 -> 0 | F48: =+ESTIMACION!N50 -> 0 | J48: =+IF(F48=0,"N/A",H48/F48) -> N/A | K48: =+H48-F48 -> 0 | M48: =IF(F48=0,"N/A",J48-1) -> N/A
C49: =+ESTIMACION!C51 -> [Insertar más líneas aquí] | F49: =+ESTIMACION!N51 -> 0 | J49: =+IF(F49=0,"N/A",H49/F49) -> N/A | K49: =+H49-F49 -> 0 | M49: =IF(F49=0,"N/A",J49-1) -> N/A
C51: SUBTOTAL | F51: =SUM(F46:F49) -> 5151 | H51: =SUM(H46:H49) -> 5099 | J51: =+IF(F51=0,"N/A",H51/F51) -> 0.98990487 | K51: =SUM(K46:K49) -> -52 | M51: =IF(F51=0,"N/A",J51-1) -> -0.010095127
B53: 1.D | C53: AMORTIZACION HW/SW
F54: TOTAL PREVISTO | H54: TOTAL FINAL | K54: DESVIACIÓN
C55: ELEMENTO HW/SW | F55: DIAS | G55: COSTE | H55: DIAS | I55: COSTE | J55: % | K55: DIAS | L55: COSTE | M55: %
C56: =+ESTIMACION!C58 -> DES1 | F56: =+ESTIMACION!L58 -> 360 | G56: =+ESTIMACION!N58 -> 566.66667 | H56: 360 | I56: =+IF(F56=0,"N/A",H56*ESTIMACION!M58*ESTIMACION!I58*ESTIMACION!H58) -> 566.66667 | J56: =+IF(F56=0,"N/A",H56/F56) -> 1 | K56: =+H56-F56 -> 0 | L56: =IF(F56=0,"N/A",+I56-G56) -> 0 | M56: =IF(F56=0,"N/A",J56-1) -> 0
C57: =+ESTIMACION!C59 -> DES2 | F57: =+ESTIMACION!L59 -> 360 | G57: =+ESTIMACION!N59 -> 800 | H57: 360 | I57: =+IF(F57=0,"N/A",H57*ESTIMACION!M59*ESTIMACION!I59*ESTIMACION!H59) -> 800 | J57: =+IF(F57=0,"N/A",H57/F57) -> 1 | K57: =+H57-F57 -> 0 | L57: =IF(F57=0,"N/A",+I57-G57) -> 0 | M57: =IF(F57=0,"N/A",J57-1) -> 0
C58: =+ESTIMACION!C60 -> SERV1 | F58: =+ESTIMACION!L60 -> 255 | G58: =+ESTIMACION!N60 -> 136 | H58: 255 | I58: =+IF(F58=0,"N/A",H58*ESTIMACION!M60*ESTIMACION!I60*ESTIMACION!H60) -> 136 | J58: =+IF(F58=0,"N/A",H58/F58) -> 1 | K58: =+H58-F58 -> 0 | L58: =IF(F58=0,"N/A",+I58-G58) -> 0 | M58: =IF(F58=0,"N/A",J58-1) -> 0
C59: =+ESTIMACION!C61 -> TAB1 | F59: =+ESTIMACION!L61 -> 0 | G59: =+ESTIMACION!N61 -> 0 | H59: 0 | I59: =+IF(F59=0,"N/A",H59*ESTIMACION!M61*ESTIMACION!I61*ESTIMACION!H61) -> N/A | J59: =+IF(F59=0,"N/A",H59/F59) -> N/A | K59: =+H59-F59 -> 0 | L59: =IF(F59=0,"N/A",+I59-G59) -> N/A | M59: =IF(F59=0,"N/A",J59-1) -> N/A
C60: =+ESTIMACION!C62 -> MIND445 | F60: =+ESTIMACION!L62 -> 30 | G60: =+ESTIMACION!N62 -> 8.3333333 | H60: 30 | I60: =+IF(F60=0,"N/A",H60*ESTIMACION!M62*ESTIMACION!I62*ESTIMACION!H62) -> 8.3333333 | J60: =+IF(F60=0,"N/A",H60/F60) -> 1 | K60: =+H60-F60 -> 0 | L60: =IF(F60=0,"N/A",+I60-G60) -> 0 | M60: =IF(F60=0,"N/A",J60-1) -> 0
C61: =+ESTIMACION!C63 -> DWCS6 | F61: =+ESTIMACION!L63 -> 0 | G61: =+ESTIMACION!N63 -> 0 | H61: 0 | I61: =+IF(F61=0,"N/A",H61*ESTIMACION!M63*ESTIMACION!I63*ESTIMACION!H63) -> N/A | J61: =+IF(F61=0,"N/A",H61/F61) -> N/A | K61: =+H61-F61 -> 0 | L61: =IF(F61=0,"N/A",+I61-G61) -> N/A | M61: =IF(F61=0,"N/A",J61-1) -> N/A
C62: =+ESTIMACION!C64 -> MVS2010 | F62: =+ESTIMACION!L64 -> 240 | G62: =+ESTIMACION!N64 -> 833.33333 | H62: 240 | I62: =+IF(F62=0,"N/A",H62*ESTIMACION!M64*ESTIMACION!I64*ESTIMACION!H64) -> 833.33333 | J62: =+IF(F62=0,"N/A",H62/F62) -> 1 | K62: =+H62-F62 -> 0 | L62: =IF(F62=0,"N/A",+I62-G62) -> 0 | M62: =IF(F62=0,"N/A",J62-1) -> 0
C63: =+ESTIMACION!C65 -> [Insertar] | F63: =+ESTIMACION!L65 -> 0 | G63: =+ESTIMACION!N65 -> 0 | H63: 0 | I63: =+IF(F63=0,"N/A",H63*ESTIMACION!M65*ESTIMACION!I65*ESTIMACION!H65) -> N/A | J63: =+IF(F63=0,"N/A",H63/F63) -> N/A | K63: =+H63-F63 -> 0 | L63: =IF(F63=0,"N/A",+I63-G63) -> N/A | M63: =IF(F63=0,"N/A",J63-1) -> N/A
C65: SUBTOTAL | F65: =SUM(F56:F63) -> 1245 | G65: =SUM(G56:G63) -> 2344.3333 | H65: =SUM(H56:H63) -> 1245 | I65: =SUM(I56:I63) -> 2344.3333 | J65: =+IF(F65=0,"N/A",H65/F65) -> 1 | K65: =SUM(K56:K63) -> 0 | L65: =SUM(L56:L63) -> 0 | M65: =IF(F65=0,"N/A",J65-1) -> 0
B67: 1.E | C67: OTROS GASTOS
F68: TOTAL PREVISTO | H68: TOTAL FINAL | K68: DESVIACIÓN
C69: DESCRIPCIÓN DEL GASTO | F69: COSTE | H69: COSTE | J69: % | K69: COSTE | M69: %
C70: =+ESTIMACION!C73 -> MATERIAL FUNGIBLE | F70: =+ESTIMACION!N73 -> 330 | H70: 330 | J70: =+IF(F70=0,"N/A",H70/F70) -> 1 | K70: =+H70-F70 -> 0 | M70: =IF(F70=0,"N/A",J70-1) -> 0
C71: =+ESTIMACION!C74 -> MATERIAL FUNGIBLE RESTO | F71: =+ESTIMACION!N74 -> 495 | H71: 695 | J71: =+IF(F71=0,"N/A",H71/F71) -> 1.4040404 | K71: =+H71-F71 -> 200 | M71: =IF(F71=0,"N/A",J71-1) -> 0.4040404
C72: =+ESTIMACION!C75 -> VIAJES | F72: =+ESTIMACION!N75 -> 990 | H72: =165 * 4 + 375*2 -> 1410 | J72: =+IF(F72=0,"N/A",H72/F72) -> 1.4242424 | K72: =+H72-F72 -> 420 | M72: =IF(F72=0,"N/A",J72-1) -> 0.42424242
C73: =+ESTIMACION!C77 -> [Insertar más líneas aquí] | F73: =+ESTIMACION!L78 -> 0 | J73: =+IF(F73=0,"N/A",H73/F73) -> N/A | K73: =+H73-F73 -> 0 | M73: =IF(F73=0,"N/A",J73-1) -> N/A
C75: SUBTOTAL | F75: =SUM(F70:F73) -> 1815 | H75: =SUM(H70:H73) -> 2435 | J75: =+IF(F75=0,"N/A",H75/F75) -> 1.3415978 | K75: =SUM(K70:K73) -> 620 | M75: =IF(F75=0,"N/A",J75-1) -> 0.3415978
B77: 2 | C77: INGRESOS
F78: ESTIMACION | H78: REALIZADO | K78: DESVIACIÓN
C79: FACTURACIÓN | F79: PRECIO | H79: PRECIO | J79: % | K79: COSTE | M79: %
C80: VENTA | F80: =+ESTIMACION!N94 -> 97148.99 | H80: =F80 -> 97148.99 | J80: =+IF(F80=0,"N/A",H80/F80) -> 1 | K80: =+H80-F80 -> 0 | M80: =IF(F80=0,"N/A",J80-1) -> 0
C82: SUBTOTAL | F82: =SUM(F80) -> 97148.99 | H82: =SUM(H80) -> 97148.99 | J82: =+IF(F82=0,"N/A",H82/F82) -> 1 | K82: =SUM(K80) -> 0 | M82: =IF(F82=0,"N/A",J82-1) -> 0
A84: 2. BALANCE FINAL DEL PROYECTO
F86: TOTAL PREVISTO | H86: TOTAL FINAL | K86: DESVIACIÓN
C87: CONTINGENCIA | F87: COSTE | H87: COSTE | J87: % | K87: COSTE | M87: %
C88: =+ESTIMACION!C88 -> PERSONAL | F88: =+G30 -> 67102.159 | H88: =+I30 -> 69254.361 | J88: =+IF(F88=0,"N/A",H88/F88) -> 1.0320735 | K88: =+L30 -> 2152.2017 | M88: =IF(F88=0,"N/A",J88-1) -> 0.032073509
C89: =+ESTIMACION!C89 -> SUBCONTRATACIONES | F89: =+F40 -> 0 | H89: =+H40 -> 2228 | J89: =+IF(F89=0,"N/A",H89/F89) -> N/A | K89: =+H89-F89 -> 2228 | M89: =IF(F89=0,"N/A",J89-1) -> N/A
C90: =+ESTIMACION!C90 -> EQUIPAMIENTO | F90: =+F51 -> 5151 | H90: =+H51 -> 5099 | J90: =+IF(F90=0,"N/A",H90/F90) -> 0.98990487 | K90: =+H90-F90 -> -52 | M90: =IF(F90=0,"N/A",J90-1) -> -0.010095127
C91: =+ESTIMACION!C91 -> AMORTIZACION HW/SW | F91: =+G65 -> 2344.3333 | H91: =+I65 -> 2344.3333 | J91: =+IF(F91=0,"N/A",H91/F91) -> 1 | K91: =+H91-F91 -> 0 | M91: =IF(F91=0,"N/A",J91-1) -> 0
C92: =+ESTIMACION!C92 -> OTROS GASTOS | F92: =+F75 -> 1815 | H92: =+H75 -> 2435 | J92: =+IF(F92=0,"N/A",H92/F92) -> 1.3415978 | K92: =+H92-F92 -> 620 | M92: =IF(F92=0,"N/A",J92-1) -> 0.3415978
C93: INGRESOS | F93: =+F82 -> 97148.99 | H93: =+H82 -> 97148.99 | J93: =+IF(F93=0,"N/A",H93/F93) -> 1 | K93: =+K82 -> 0 | M93: =+M82 -> 0
C94: BENEFICIOS | F94: =+F93-SUM(F88:G92) -> 20736.498 | H94: =+H93-SUM(H88:I92) -> 15788.296 | J94: =+IF(F94=0,"N/A",H94/F94) -> 0.76137717 | K94: =SUM(K88:K92) -> 4948.2017 | M94: =IF(F94=0,"N/A",J94-1) -> -0.23862283
A98: 3. INDICADORES ECONOMICOS, FINANCIEROS Y DE OCUPACION
B100: 3.A | C100: CONSUMO Y REMANENTE DE RECURSOS SEGÚN TIPO
